{
  "menu": [
    {
      "kategori": "pizza",
      "nama": "Meat Lover",
      "deskripsi": "Irisan sosis sapi, daging sapi cincang, burger sapi, sosis ayam.",
      "harga": 49500,
      "gambar": "meat-lover.jpg"
    },
    {
      "kategori": "pizza",
      "nama": "Super Supreme",
      "deskripsi": "Daging ayam dan sapi asap, daging sapi cincang, burger sapi, jamur, paprika merah dan paprika hijau.",
      "harga": 49500,
      "gambar": "supreme.jpg"
    },
    {
      "kategori": "pizza",
      "nama": "Tuna Melt",
      "deskripsi": "Irisan daging ikan tuna, butiran jagung, saus mayonnaise.",
      "harga": 49500,
      "gambar": "tuna-melt.jpg"
    },
    {
      "kategori": "pizza",
      "nama": "American Favourite",
      "deskripsi": "Pepperoni sapi, daging sapi cincang, jamur.",
      "harga": 49500,
      "gambar": "american-favourite.jpg"
    },
    {
      "kategori": "pasta",
      "nama": "Beef Spaghetti",
      "deskripsi": "Pepperoni sapi, daging sapi cincang, jamur.",
      "harga": 43000,
      "gambar": "beef-spaghetti.jpg"
    },
    {
      "kategori": "pasta",
      "nama": "Beef Lasagna",
      "deskripsi": "Dipanggang, daging sapi cincang. krim putih lembut di tiap lapisan.",
      "harga": 48000,
      "gambar": "beef-lasagna.jpg"
    },
    {
      "kategori": "pasta",
      "nama": "Creamy Beef Fettuccine",
      "deskripsi": "Daging sapi asap dan jamur, ditumis dengan saus krim lembut.",
      "harga": 43000,
      "gambar": "creamy-beef-fettuccine.jpg"
    },
    {
      "kategori": "rice",
      "nama": "Meatballs Beef Mushroom",
      "deskripsi": "Bola daging sapi dengan saus daging sapi cincang dan jamur.",
      "harga": 40000,
      "gambar": "meatballs-beef-mushroom.jpg"
    },
    {
      "kategori": "rice",
      "nama": "Black Pepper Chicken",
      "deskripsi": "Ayam dengan saus lada hitam.",
      "harga": 40000,
      "gambar": "black-pepper-chicken.jpg"
    },
    {
      "kategori": "rice",
      "nama": "Oriental Chicken",
      "deskripsi": "Daging ayam berpadu dengan saus oriental.",
      "harga": 40000,
      "gambar": "oriental-chicken.jpg"
    },
    {
      "kategori": "drink",
      "nama": "Choco Mint",
      "deskripsi": "Minuman coklat aroma mint segar",
      "harga": 24000,
      "gambar": "choco-mint.jpg"
    },
    {
      "kategori": "drink",
      "nama": "Toffee Coffee",
      "deskripsi": "Kopi spesial dengan kekentalan yang pas",
      "harga": 24000,
      "gambar": "toffee-coffee.jpg"
    },
    {
      "kategori": "drink",
      "nama": "Green Tea Shake",
      "deskripsi": "Terbuat dari teh hijau asli dan pilihan",
      "harga": 24000,
      "gambar": "green-tea-shake.jpg"
    },
    {
      "kategori": "drink",
      "nama": "Strawberry Milkshake",
      "deskripsi": "Perpaduan strawberi dan susu yang asli",
      "harga": 24000,
      "gambar": "strawberry-milkshake.jpg"
    },
    {
      "kategori": "drink",
      "nama": "Chocolate Milkshake",
      "deskripsi": "Coklat pilihan khas malang",
      "harga": 24000,
      "gambar": "chocolate-milkshake.jpg"
    }
  ]
}